arcade_linear/__init__.py
arcade_linear/__main__.py
arcade_linear/client.py
arcade_linear/constants.py
arcade_linear/models/__init__.py
arcade_linear/models/enums.py
arcade_linear/models/mappers.py
arcade_linear/models/api_responses/__init__.py
arcade_linear/models/api_responses/common.py
arcade_linear/models/api_responses/cycles.py
arcade_linear/models/api_responses/issues.py
arcade_linear/models/api_responses/metadata.py
arcade_linear/models/api_responses/projects.py
arcade_linear/models/tool_outputs/__init__.py
arcade_linear/models/tool_outputs/comments.py
arcade_linear/models/tool_outputs/common.py
arcade_linear/models/tool_outputs/cycles.py
arcade_linear/models/tool_outputs/github.py
arcade_linear/models/tool_outputs/initiatives.py
arcade_linear/models/tool_outputs/issues.py
arcade_linear/models/tool_outputs/metadata.py
arcade_linear/models/tool_outputs/projects.py
arcade_linear/models/tool_outputs/user_context.py
arcade_linear/tools/__init__.py
arcade_linear/tools/comments.py
arcade_linear/tools/cycles.py
arcade_linear/tools/github.py
arcade_linear/tools/initiatives.py
arcade_linear/tools/issue_actions.py
arcade_linear/tools/issues.py
arcade_linear/tools/metadata.py
arcade_linear/tools/project_comments.py
arcade_linear/tools/projects.py
arcade_linear/tools/teams.py
arcade_linear/tools/user_context.py
arcade_linear/utils/__init__.py
arcade_linear/utils/comment_utils.py
arcade_linear/utils/cycle_utils.py
arcade_linear/utils/date_utils.py
arcade_linear/utils/fuzzy_utils.py
arcade_linear/utils/github_utils.py
arcade_linear/utils/initiative_utils.py
arcade_linear/utils/issue_utils.py
arcade_linear/utils/pagination_utils.py
arcade_linear/utils/project_comment_utils.py
arcade_linear/utils/project_utils.py
arcade_linear/utils/response_utils.py
arcade_linear/utils/search_utils.py
arcade_linear/utils/team_utils.py
arcade_linear/utils/user_context_utils.py
arcade_linear-3.2.0.dist-info/METADATA
arcade_linear-3.2.0.dist-info/WHEEL
arcade_linear-3.2.0.dist-info/entry_points.txt
arcade_linear-3.2.0.dist-info/licenses/LICENSE
arcade_linear-3.2.0.dist-info/RECORD
