Metadata-Version: 2.4
Name: arcade_linear
Version: 3.2.0
Summary: Arcade tools designed for LLMs to interact with Linear
Author-email: Arcade <dev@arcade.dev>
License: Proprietary - Arcade Software License Agreement v1.0
License-File: LICENSE
Requires-Python: >=3.10
Requires-Dist: arcade-mcp-server<2.0.0,>=1.9.2
Requires-Dist: dateparser<2.0.0,>=1.1.8
Requires-Dist: gql[aiohttp]<4.0.0,>=3.5.0
Requires-Dist: rapidfuzz<4.0.0,>=3.0.0
Requires-Dist: typing-extensions<5.0.0,>=4.8.0
Provides-Extra: dev
Requires-Dist: arcade-mcp[evals]<2.0.0,>=1.5.6; extra == 'dev'
Requires-Dist: mypy<1.6.0,>=1.5.1; extra == 'dev'
Requires-Dist: pre-commit<3.5.0,>=3.4.0; extra == 'dev'
Requires-Dist: pytest-asyncio<0.25.0,>=0.24.0; extra == 'dev'
Requires-Dist: pytest-cov<4.1.0,>=4.0.0; extra == 'dev'
Requires-Dist: pytest-mock<3.12.0,>=3.11.1; extra == 'dev'
Requires-Dist: pytest<8.4.0,>=8.3.0; extra == 'dev'
Requires-Dist: ruff<0.8.0,>=0.7.4; extra == 'dev'
Requires-Dist: tox<4.12.0,>=4.11.1; extra == 'dev'
Requires-Dist: types-dateparser>=1.2.2.20250627; extra == 'dev'
